calibur/__init__.py
calibur/conventions.py
calibur/data.npz
calibur/generic_utils.py
calibur/graphic_utils.py
calibur/ndarray_extension.py
calibur/projection.py
calibur/rays.py
calibur/raytracing.py
calibur/render_pipelines.py
calibur/resources.py
calibur/sh_int_64.npz
calibur/shading.py
calibur/version.py
calibur/viewport.py
calibur-0.0.1.dist-info/LICENSE
calibur-0.0.1.dist-info/METADATA
calibur-0.0.1.dist-info/WHEEL
calibur-0.0.1.dist-info/top_level.txt
calibur-0.0.1.dist-info/RECORD
