Metadata-Version: 2.1
Name: calibur
Version: 0.0.1
Summary: Toolbox for converting rotations, camera calibration matrices, transforms and spaces.
Home-page: https://github.com/eliphatfs/calibur
Author: flandre.info
Author-email: flandre@scarletx.cn
License: UNKNOWN
Platform: UNKNOWN
Classifier: Programming Language :: Python :: 3 :: Only
Classifier: License :: OSI Approved :: Apache Software License
Classifier: Operating System :: OS Independent
Requires-Python: ~=3.7
Requires-Dist: numpy
Requires-Dist: typing-extensions
